<?xml version="1.0" encoding="UTF-8"?>
<form>
	<fields name="params" >
		<fieldset name="params" >
			<field name="contact_extra_fields"
				type="Repeatable"
				icon="list"
				description="PLG_TINY_FIELD_TEMPLATE_FIELD_ELEMENTS_DESC"
				label="PLG_TINY_FIELD_TEMPLATE_FIELD_ELEMENTS_LABEL"
				default="{'template':['Layout','Simple snippet'],'location':['layout1.html','snippet1.html'],'description':['HTMLLayout','Simple HTML snippet']}">
				<fields name="params">
					<fieldset hidden="true" name="contact_extra_fields_modal" repeat="true">
						<field 
							name="extrafield_type"
							label="Select field type"
							type="list" 
							default=""
						>
							
							<option value=" ">Select</option>
							<option value="text">Text</option>
							<option value="list">List</option>
							<option value="checkbox">Checkbox</option>
						
						</field>
						
						<field 
							name="extrafield_name"
							label="Field name"
							type="text" 
							default=" "
						>
		
						</field>

						<field 
							name="extrafield_label"
							label="Field label"
							type="text" 
							default=" "
						>
		
						</field>

						<field name="location"
							label="PLG_TINY_FIELD_TEMPLATE_FIELD_LOCATION_LABEL"
							description="PLG_TINY_FIELD_TEMPLATE_LOCATION_DESC"
							size="30"
							type="filelist"
							directory="media/editors/tinymce/templates"
							exclude="index.html"
							hide_default="true"
							hide_none="true" />
						<field name="description"
							label="PLG_TINY_FIELD_TEMPLATE_FIELD_DESCRIPTION_LABEL"
							size="30"
							type="textarea" />
					</fieldset>
				</fields>
			</field>
		</fieldset>
	</fields>
</form>